qodacode/__init__.py
qodacode/ai_explainer.py
qodacode/audit_log.py
qodacode/auth.py
qodacode/cache.py
qodacode/cli.py
qodacode/daemon.py
qodacode/engine_installer.py
qodacode/git_scanner.py
qodacode/github.py
qodacode/interactive.py
qodacode/mcp_server.py
qodacode/orchestrator.py
qodacode/osv.py
qodacode/rate_limiter.py
qodacode/reporter.py
qodacode/scanner.py
qodacode/secrets.py
qodacode/security_hooks.py
qodacode/_core/__init__.py
qodacode/_core/_fallback.py
qodacode/context/__init__.py
qodacode/context/deduplicator.py
qodacode/context/semantic.py
qodacode/engines/__init__.py
qodacode/engines/base.py
qodacode/engines/gitleaks_runner.py
qodacode/engines/osv_runner.py
qodacode/engines/semgrep_runner.py
qodacode/models/__init__.py
qodacode/models/issue.py
qodacode/premium/__init__.py
qodacode/premium/alignment/__init__.py
qodacode/premium/alignment/auditor.py
qodacode/premium/alignment/scenarios.py
qodacode/premium/alignment/verdict.py
qodacode/rules/__init__.py
qodacode/rules/base.py
qodacode/rules/dependencies.py
qodacode/rules/maintainability.py
qodacode/rules/operability.py
qodacode/rules/robustness.py
qodacode/rules/security.py
qodacode/typosquatting/__init__.py
qodacode/typosquatting/database.py
qodacode/typosquatting/detector.py
qodacode/typosquatting/similarity.py
qodacode/utils/__init__.py
qodacode/utils/binaries.py
qodacode/utils/masking.py
qodacode/utils/verdict.py
qodacode-1.0.3.dist-info/METADATA
qodacode-1.0.3.dist-info/WHEEL
qodacode-1.0.3.dist-info/entry_points.txt
qodacode-1.0.3.dist-info/licenses/LICENSE
qodacode-1.0.3.dist-info/RECORD
