Metadata-Version: 2.4
Name: qodacode
Version: 1.0.3
Summary: AI Governance Platform - Security + Alignment for AI Agents
Author: Nelson Padilla
License: AGPL-3.0-or-later
License-File: LICENSE
Keywords: ai-governance,alignment,code-analysis,security,static-analysis
Classifier: Development Status :: 4 - Beta
Classifier: Environment :: Console
Classifier: Intended Audience :: Developers
Classifier: License :: OSI Approved :: GNU Affero General Public License v3
Classifier: Programming Language :: Python :: 3
Classifier: Programming Language :: Python :: 3.10
Classifier: Programming Language :: Python :: 3.11
Classifier: Programming Language :: Python :: 3.12
Classifier: Programming Language :: Python :: 3.13
Classifier: Programming Language :: Python :: 3.14
Classifier: Topic :: Security
Classifier: Topic :: Software Development :: Quality Assurance
Classifier: Topic :: Software Development :: Testing
Requires-Python: >=3.10
Requires-Dist: anthropic>=0.18
Requires-Dist: click>=8.1
Requires-Dist: httpx>=0.25
Requires-Dist: mcp>=1.0
Requires-Dist: openai>=1.0
Requires-Dist: prompt-toolkit>=3.0
Requires-Dist: pydantic>=2.0
Requires-Dist: questionary>=2.0
Requires-Dist: rich>=13.0
Requires-Dist: semgrep>=1.50
Requires-Dist: textual>=0.40
Requires-Dist: tree-sitter-javascript>=0.21
Requires-Dist: tree-sitter-python>=0.21
Requires-Dist: tree-sitter-typescript>=0.21
Requires-Dist: tree-sitter>=0.21
Requires-Dist: watchdog>=3.0
Provides-Extra: dev
Requires-Dist: mypy>=1.0; extra == 'dev'
Requires-Dist: pytest-cov>=4.0; extra == 'dev'
Requires-Dist: pytest>=7.0; extra == 'dev'
Requires-Dist: ruff>=0.1; extra == 'dev'
Provides-Extra: embeddings
Requires-Dist: chromadb>=0.4; extra == 'embeddings'
Requires-Dist: numpy>=1.24; extra == 'embeddings'
Requires-Dist: sentence-transformers>=2.2; extra == 'embeddings'
Provides-Extra: full
Requires-Dist: chromadb>=0.4; extra == 'full'
Requires-Dist: jinja2>=3.0; extra == 'full'
Requires-Dist: litellm>=1.0; extra == 'full'
Requires-Dist: mypy>=1.0; extra == 'full'
Requires-Dist: networkx>=3.0; extra == 'full'
Requires-Dist: numpy>=1.24; extra == 'full'
Requires-Dist: pytest-cov>=4.0; extra == 'full'
Requires-Dist: pytest>=7.0; extra == 'full'
Requires-Dist: ruff>=0.1; extra == 'full'
Requires-Dist: sentence-transformers>=2.2; extra == 'full'
Requires-Dist: weasyprint>=60.0; extra == 'full'
Provides-Extra: premium
Requires-Dist: jinja2>=3.0; extra == 'premium'
Requires-Dist: litellm>=1.0; extra == 'premium'
Requires-Dist: networkx>=3.0; extra == 'premium'
Requires-Dist: weasyprint>=60.0; extra == 'premium'
